[
    {
        "registration_number": {
            "registration_number": "CS-TJN"
        },
        "model": {
            "name": "Airbus A321neo",
            "seating_capacity": 216,
            "max_range": 7400.0,
            "fuel_capacity": 29680.0,
            "cruising_speed": 833.0,
            "manufacturer": {
                "name": "Airbus"
            },
            "features": [
                "Wi-Fi",
                "LED Lighting",
                "HEPA Filters"
            ]
        },
        "seating_configuration": {
            "economy_seats": 200,
            "premium_economy_seats": 0,
            "business_seats": 16,
            "first_seats": 0
        },
        "manufactoring_date": "2019-05-15",
        "last_maintenance": "2023-11-10",
        "image": "iVBORw0KGgoAAAANSUhEUgAAAAEAAAABCAYAAAAfFcSJAAAADUlEQVR42mP8z8BQDwAEhQGAhKmMIQAAAABJRU5ErkJggg==",
        "operational_hours": 12500.5,
        "total_flight_hours": 12000.0,
        "max_flight_hours_until_maintenance": 800,
        "max_days_until_maintenance": 90,
        "status": "AVAILABLE"
    },
    {
        "registration_number": {
            "registration_number": "A6-EQP"
        },
        "model": {
            "name": "Boeing 777-300ER",
            "seating_capacity": 380,
            "max_range": 13649.0,
            "fuel_capacity": 181283.0,
            "cruising_speed": 892.0,
            "manufacturer": {
                "name": "Boeing"
            },
            "features": [
                "In-flight Entertainment",
                "Lie-flat Seats",
                "Onboard Lounge"
            ]
        },
        "seating_configuration": {
            "economy_seats": 306,
            "premium_economy_seats": 24,
            "business_seats": 42,
            "first_seats": 8
        },
        "manufactoring_date": "2016-08-22",
        "last_maintenance": "2024-02-15",
        "image": "iVBORw0KGgoAAAANSUhEUgAAAAEAAAABCAYAAAAfFcSJAAAADUlEQVR42mP8z8BQDwAEhQGAhKmMIQAAAABJRU5ErkJggg==",
        "operational_hours": 35000.0,
        "total_flight_hours": 33500.0,
        "max_flight_hours_until_maintenance": 1000,
        "max_days_until_maintenance": 120,
        "status": "IN_FLIGHT"
    },
    {
        "registration_number": {
            "registration_number": "PR-PJN"
        },
        "model": {
            "name": "Embraer E195-E2",
            "seating_capacity": 136,
            "max_range": 4815.0,
            "fuel_capacity": 13690.0,
            "cruising_speed": 870.0,
            "manufacturer": {
                "name": "Embraer"
            },
            "features": [
                "No Middle Seat",
                "Large Windows"
            ]
        },
        "seating_configuration": {
            "economy_seats": 136,
            "premium_economy_seats": 0,
            "business_seats": 0,
            "first_seats": 0
        },
        "manufactoring_date": "2020-01-10",
        "last_maintenance": "2024-01-05",
        "image": "iVBORw0KGgoAAAANSUhEUgAAAAEAAAABCAYAAAAfFcSJAAAADUlEQVR42mP8z8BQDwAEhQGAhKmMIQAAAABJRU5ErkJggg==",
        "operational_hours": 8500.2,
        "total_flight_hours": 8100.0,
        "max_flight_hours_until_maintenance": 600,
        "max_days_until_maintenance": 90,
        "status": "AVAILABLE"
    },
    {
        "registration_number": {
            "registration_number": "EI-HAY"
        },
        "model": {
            "name": "Boeing 737 MAX 8",
            "seating_capacity": 189,
            "max_range": 6570.0,
            "fuel_capacity": 25816.0,
            "cruising_speed": 839.0,
            "manufacturer": {
                "name": "Boeing"
            },
            "features": [
                "Sky Interior",
                "USB Outlets"
            ]
        },
        "seating_configuration": {
            "economy_seats": 189,
            "premium_economy_seats": 0,
            "business_seats": 0,
            "first_seats": 0
        },
        "manufactoring_date": "2021-03-12",
        "last_maintenance": "2024-03-20",
        "image": "iVBORw0KGgoAAAANSUhEUgAAAAEAAAABCAYAAAAfFcSJAAAADUlEQVR42mP8z8BQDwAEhQGAhKmMIQAAAABJRU5ErkJggg==",
        "operational_hours": 6200.0,
        "total_flight_hours": 6000.0,
        "max_flight_hours_until_maintenance": 750,
        "max_days_until_maintenance": 90,
        "status": "UNDER_MAINTENANCE"
    },
    {
        "registration_number": {
            "registration_number": "D-AIXI"
        },
        "model": {
            "name": "Airbus A350-900",
            "seating_capacity": 293,
            "max_range": 15000.0,
            "fuel_capacity": 141000.0,
            "cruising_speed": 903.0,
            "manufacturer": {
                "name": "Airbus"
            },
            "features": [
                "Quiet Cabin",
                "Advanced Climate Control",
                "Wi-Fi"
            ]
        },
        "seating_configuration": {
            "economy_seats": 224,
            "premium_economy_seats": 21,
            "business_seats": 48,
            "first_seats": 0
        },
        "manufactoring_date": "2018-11-05",
        "last_maintenance": "2023-12-01",
        "image": "iVBORw0KGgoAAAANSUhEUgAAAAEAAAABCAYAAAAfFcSJAAAADUlEQVR42mP8z8BQDwAEhQGAhKmMIQAAAABJRU5ErkJggg==",
        "operational_hours": 21000.5,
        "total_flight_hours": 20500.0,
        "max_flight_hours_until_maintenance": 1200,
        "max_days_until_maintenance": 180,
        "status": "IN_FLIGHT"
    },
    {
        "registration_number": {
            "registration_number": "D-ACKL"
        },
        "model": {
            "name": "Bombardier CRJ900",
            "seating_capacity": 90,
            "max_range": 2871.0,
            "fuel_capacity": 8822.0,
            "cruising_speed": 829.0,
            "manufacturer": {
                "name": "Bombardier"
            },
            "features": [
                "Regional Connectivity",
                "Fast Turnaround"
            ]
        },
        "seating_configuration": {
            "economy_seats": 79,
            "premium_economy_seats": 0,
            "business_seats": 11,
            "first_seats": 0
        },
        "manufactoring_date": "2010-07-14",
        "last_maintenance": "2023-09-15",
        "image": "iVBORw0KGgoAAAANSUhEUgAAAAEAAAABCAYAAAAfFcSJAAAADUlEQVR42mP8z8BQDwAEhQGAhKmMIQAAAABJRU5ErkJggg==",
        "operational_hours": 41000.0,
        "total_flight_hours": 39500.0,
        "max_flight_hours_until_maintenance": 500,
        "max_days_until_maintenance": 60,
        "status": "AVAILABLE"
    },
    {
        "registration_number": {
            "registration_number": "EC-NJK"
        },
        "model": {
            "name": "ATR 72-600",
            "seating_capacity": 72,
            "max_range": 1528.0,
            "fuel_capacity": 5000.0,
            "cruising_speed": 510.0,
            "manufacturer": {
                "name": "ATR"
            },
            "features": [
                "Propeller Driven",
                "Short Runway Capable"
            ]
        },
        "seating_configuration": {
            "economy_seats": 72,
            "premium_economy_seats": 0,
            "business_seats": 0,
            "first_seats": 0
        },
        "manufactoring_date": "2019-09-30",
        "last_maintenance": "2024-04-10",
        "image": "iVBORw0KGgoAAAANSUhEUgAAAAEAAAABCAYAAAAfFcSJAAAADUlEQVR42mP8z8BQDwAEhQGAhKmMIQAAAABJRU5ErkJggg==",
        "operational_hours": 10500.0,
        "total_flight_hours": 9800.0,
        "max_flight_hours_until_maintenance": 400,
        "max_days_until_maintenance": 45,
        "status": "AVAILABLE"
    },
    {
        "registration_number": {
            "registration_number": "N650GA"
        },
        "model": {
            "name": "Gulfstream G650ER",
            "seating_capacity": 13,
            "max_range": 13890.0,
            "fuel_capacity": 18400.0,
            "cruising_speed": 956.0,
            "manufacturer": {
                "name": "Gulfstream Aerospace"
            },
            "features": [
                "Private Suite",
                "Luxury Interior",
                "Ultra Long Range"
            ]
        },
        "seating_configuration": {
            "economy_seats": 0,
            "premium_economy_seats": 0,
            "business_seats": 13,
            "first_seats": 0
        },
        "manufactoring_date": "2022-02-18",
        "last_maintenance": "2024-01-20",
        "image": "iVBORw0KGgoAAAANSUhEUgAAAAEAAAABCAYAAAAfFcSJAAAADUlEQVR42mP8z8BQDwAEhQGAhKmMIQAAAABJRU5ErkJggg==",
        "operational_hours": 1500.0,
        "total_flight_hours": 1400.0,
        "max_flight_hours_until_maintenance": 600,
        "max_days_until_maintenance": 90,
        "status": "INACTIVE"
    },
    {
        "registration_number": {
            "registration_number": "N123CL"
        },
        "model": {
            "name": "Cessna Citation Longitude",
            "seating_capacity": 12,
            "max_range": 6482.0,
            "fuel_capacity": 6600.0,
            "cruising_speed": 895.0,
            "manufacturer": {
                "name": "Cessna"
            },
            "features": [
                "Quiet Cabin",
                "Flat Floor",
                "Business Jet"
            ]
        },
        "seating_configuration": {
            "economy_seats": 0,
            "premium_economy_seats": 0,
            "business_seats": 12,
            "first_seats": 0
        },
        "manufactoring_date": "2023-05-01",
        "last_maintenance": "2023-11-05",
        "image": "iVBORw0KGgoAAAANSUhEUgAAAAEAAAABCAYAAAAfFcSJAAAADUlEQVR42mP8z8BQDwAEhQGAhKmMIQAAAABJRU5ErkJggg==",
        "operational_hours": 450.0,
        "total_flight_hours": 400.0,
        "max_flight_hours_until_maintenance": 500,
        "max_days_until_maintenance": 60,
        "status": "AVAILABLE"
    },
    {
        "registration_number": {
            "registration_number": "VH-OQB"
        },
        "model": {
            "name": "Airbus A380-800",
            "seating_capacity": 485,
            "max_range": 14800.0,
            "fuel_capacity": 320000.0,
            "cruising_speed": 903.0,
            "manufacturer": {
                "name": "Airbus"
            },
            "features": [
                "Double Deck",
                "Onboard Bar",
                "Shower Spas"
            ]
        },
        "seating_configuration": {
            "economy_seats": 341,
            "premium_economy_seats": 60,
            "business_seats": 70,
            "first_seats": 14
        },
        "manufactoring_date": "2008-12-15",
        "last_maintenance": "2023-08-10",
        "image": "iVBORw0KGgoAAAANSUhEUgAAAAEAAAABCAYAAAAfFcSJAAAADUlEQVR42mP8z8BQDwAEhQGAhKmMIQAAAABJRU5ErkJggg==",
        "operational_hours": 55000.0,
        "total_flight_hours": 53000.0,
        "max_flight_hours_until_maintenance": 1500,
        "max_days_until_maintenance": 180,
        "status": "AVAILABLE"
    }
]